ibkr_oauth_flow/__init__.py
ibkr_oauth_flow/access_token.py
ibkr_oauth_flow/bearer_token.py
ibkr_oauth_flow/const.py
ibkr_oauth_flow/logout.py
ibkr_oauth_flow/sso.py
ibkr_oauth_flow/tickle.py
ibkr_oauth_flow/util.py
ibkr_oauth_flow-0.1.0.dist-info/METADATA
ibkr_oauth_flow-0.1.0.dist-info/WHEEL
ibkr_oauth_flow-0.1.0.dist-info/top_level.txt
ibkr_oauth_flow-0.1.0.dist-info/RECORD
