Metadata-Version: 2.2
Name: ibkr-oauth-flow
Version: 0.1.0
Summary: Add your description here
Requires-Python: >=3.11
Requires-Dist: cryptography>=44.0.2
Requires-Dist: pre-commit>=4.1.0
Requires-Dist: pyjwt>=2.10.1
Requires-Dist: pyyaml>=6.0.2
Requires-Dist: requests>=2.32.3
Requires-Dist: ruff>=0.9.9
